{
	"id": -1,
	"name": "Qwant",
	"description": "Qwant is a French search engine that launched in February 2013. Qwant claims to respect the privacy of its users by not tracking them for advertising purposes or reselling their personal data, as well as being impartial in the display of results.",
	"links": {
		"website": [
			"https://qwant.com",
			"https://en.wikipedia.org/wiki/Qwant"
		]
	},
	"path": {
		"120-136": [
			[
				897,
				-94
			],
			[
				897,
				-88
			],
			[
				923,
				-88
			],
			[
				923,
				-95
			],
			[
				897,
				-95
			]
		]
	},
	"center": {
		"120-136": [
			910,
			-91
		]
	}
}
