{
	"id": -1,
	"name": "OGC Nice",
	"description": "Olympique Gymnaste Club de Nice, commonly referred to as OGC Nice or simply Nice, is a French professional football club based in Nice. The club was founded in 1904 and currently plays in Ligue 1, the top tier of French football. Nice plays its home matches at the Allianz Riviera.",
	"links": {
		"website": [
			"https://en.wikipedia.org/wiki/OGC_Nice",
			"https://www.ogcnice.com/en/"
		]
	},
	"path": {
		"240-256": [
			[
				935,
				-768
			],
			[
				935,
				-760
			],
			[
				918,
				-760
			],
			[
				918,
				-768
			]
		]
	},
	"center": {
		"240-256": [
			927,
			-764
		]
	}
}
