{
	"id": -1,
	"name": "Fuck Spez!",
	"description": "After r/place ended, everyone could only draw grayscale and later only white pixels. Everyone started to write Fuck Spez! to protest recent API changes",
	"links": {},
	"path": {
		"256-257": [
			[
				-1188,
				897
			],
			[
				1399,
				897
			],
			[
				1351,
				-910
			],
			[
				-1079,
				-913
			],
			[
				-1085,
				21
			],
			[
				-1238,
				193
			],
			[
				-1230,
				582
			]
		]
	},
	"center": {
		"256-257": [
			-107,
			-7
		]
	}
}
