{
	"id": -1,
	"name": "Flag of Peru",
	"description": "The flag of Peru, a country in western South America. The country the streamer El Zein, whose name is on this section of canvas, is from.",
	"links": {
		"website": [
			"https://en.wikipedia.org/wiki/Flag_of_Peru"
		]
	},
	"path": {
		"172-256": [
			[
				-1086,
				-641
			],
			[
				-1086,
				-642
			],
			[
				-1115,
				-671
			],
			[
				-1139,
				-647
			],
			[
				-1139,
				-646
			],
			[
				-1124,
				-631
			],
			[
				-1123,
				-631
			],
			[
				-1101,
				-653
			],
			[
				-1100,
				-653
			],
			[
				-1088,
				-640
			]
		],
		"T": [
			[
				-1115,
				-671
			],
			[
				-1139,
				-647
			],
			[
				-1139,
				-646
			],
			[
				-1124,
				-631
			],
			[
				-1123,
				-631
			],
			[
				-1101,
				-653
			],
			[
				-1100,
				-653
			],
			[
				-1088,
				-640
			],
			[
				-1087,
				-640
			],
			[
				-1086,
				-641
			],
			[
				-1086,
				-642
			]
		]
	},
	"center": {
		"172-256": [
			-1119,
			-651
		],
		"T": [
			-1119,
			-651
		]
	}
}
