{
	"id": 4199,
	"name": "El Chapulín Colorado",
	"description": "Character from the Mexican comedy created by Roberto Gomez Bolaños (Chespirito), this pixelart was made by a furry rabbit with dinosaur pajamas (Conterstine).",
	"links": {
		"website": [
			"https://es.wikipedia.org/wiki/El_Chapul%C3%ADn_Colorado",
			"https://www.twitch.tv/conterstine"
		]
	},
	"path": {
		"126-254": [
			[
				48,
				-849
			],
			[
				41,
				-859
			],
			[
				41,
				-864
			],
			[
				45,
				-861
			],
			[
				45,
				-858
			],
			[
				50,
				-857
			],
			[
				51,
				-861
			],
			[
				42,
				-869
			],
			[
				42,
				-879
			],
			[
				34,
				-894
			],
			[
				31,
				-893
			],
			[
				30,
				-888
			],
			[
				22,
				-882
			],
			[
				23,
				-878
			],
			[
				28,
				-878
			],
			[
				29,
				-875
			],
			[
				28,
				-867
			],
			[
				29,
				-865
			],
			[
				29,
				-862
			],
			[
				24,
				-862
			],
			[
				23,
				-867
			],
			[
				15,
				-867
			],
			[
				12,
				-862
			],
			[
				12,
				-857
			],
			[
				14,
				-853
			],
			[
				24,
				-852
			],
			[
				26,
				-849
			],
			[
				48,
				-849
			]
		]
	},
	"center": {
		"126-254": [
			34,
			-857
		]
	}
}
