{
	"id": -1,
	"name": "Goomba (Super Mario)",
	"description": "Goomba is a fictional species in the Super Mario franchise. In the series they serve as an easy enemy for the player to defeat.  They have become an iconic part of the franchise appearing in most Super Mario media. \n\nThis artwork in particular is taken from the 1985 video game Super Mario Bros for the NES. Their color palette has been modified to resemble the goomba's more modern appearance.",
	"links": {
		"subreddit": [
			"mario"
		]
	},
	"path": {
		"254": [
			[
				-1251,
				200
			],
			[
				-1251,
				204
			],
			[
				-1249,
				206
			],
			[
				-1249,
				208
			],
			[
				-1249,
				210
			],
			[
				-1242,
				211
			],
			[
				-1242,
				210
			],
			[
				-1241,
				210
			],
			[
				-1239,
				211
			],
			[
				-1234,
				211
			],
			[
				-1234,
				210
			],
			[
				-1233,
				205
			],
			[
				-1232,
				200
			],
			[
				-1234,
				197
			],
			[
				-1235,
				197
			],
			[
				-1236,
				195
			],
			[
				-1238,
				193
			],
			[
				-1239,
				192
			],
			[
				-1244,
				192
			]
		]
	},
	"center": {
		"254": [
			-1242,
			202
		]
	}
}
