{
	"id": -1,
	"name": "Rachid",
	"description": "Rachid is a depiction of a Fennec, an animal who lives in the Sahara desert and who is also the symbol of Algeria",
	"links": {
		"website": [
			"https://en.wikipedia.org/wiki/Fennec_fox#:~:text=The%20fennec%20is%20the%20smallest,insects%2C%20small%20mammals%20and%20birds."
		],
		"subreddit": [
			"algeria"
		],
		"discord": [
			"7AgJWv3r"
		]
	},
	"path": {
		"254": [
			[
				-768,
				330
			],
			[
				-768,
				337
			],
			[
				-766,
				339
			],
			[
				-766,
				341
			],
			[
				-764,
				343
			],
			[
				-764,
				347
			],
			[
				-761,
				350
			],
			[
				-760,
				350
			],
			[
				-759,
				351
			],
			[
				-756,
				351
			],
			[
				-755,
				350
			],
			[
				-754,
				350
			],
			[
				-750,
				346
			],
			[
				-750,
				342
			],
			[
				-749,
				341
			],
			[
				-749,
				340
			],
			[
				-747,
				338
			],
			[
				-747,
				331
			],
			[
				-746,
				330
			],
			[
				-749,
				333
			],
			[
				-750,
				333
			],
			[
				-756,
				339
			],
			[
				-759,
				339
			],
			[
				-764,
				334
			]
		]
	},
	"center": {
		"254": [
			-757,
			345
		]
	}
}
